setup.py
bin/factor
test/test_chain.py
test/test_concurrent.py
test/test_encoding.py
test/test_factor.py
test/test_logger.py
utils/__init__.py
utils/chaining.py
utils/concurrent.py
utils/encodings.py
utils/factor.py
utils/log.py
winkar_utils.egg-info/PKG-INFO
winkar_utils.egg-info/SOURCES.txt
winkar_utils.egg-info/dependency_links.txt
winkar_utils.egg-info/not-zip-safe
winkar_utils.egg-info/requires.txt
winkar_utils.egg-info/top_level.txt