Metadata-Version: 1.0
Name: winkar-utils
Version: 0.0.7
Summary: Util functions for python
Home-page: UNKNOWN
Author: WinKaR
Author-email: winkar@163.com
License: BSD
Platform: UNKNOWN
